COPYING
HISTORY.rst
INSTALL
README.rst
__init__.py
buildInstall
replayPackets
setup.py
doc/.ignore
doc/Makefile
doc/createRsts.py
doc/source/changelog.rst
doc/source/conf.py
doc/source/configuration.rst
doc/source/index.rst
doc/source/installation.rst
doc/source/intro.rst
doc/source/running.rst
doc/source/writing_objectFilters.rst
doc/source/writing_plugins.rst
doc/source/writing_responses.rst
doc/source/writing_speechRules.rst
doc/source/_generated/.ignore
doc/source/_modified/pysiriproxy_plugins_objectClasses.rst
doc/source/_modified/pysiriproxy_plugins_speechRules.rst
pysiriproxy/__init__.py
pysiriproxy/cmdline.py
pysiriproxy/constants.py
pysiriproxy/interpreter.py
pysiriproxy/packetPlayer.py
pysiriproxy/plist.py
pysiriproxy/utils.py
pysiriproxy/config/pysiriproxy.cfg
pysiriproxy/config/plugins/__init__.py
pysiriproxy/config/plugins/buttonTest.py
pysiriproxy/config/plugins/locationTest.py
pysiriproxy/config/plugins/resetPlugin.py
pysiriproxy/config/plugins/testPlugin.py
pysiriproxy/config/scripts/gen_certs.sh
pysiriproxy/config/scripts/openssl.cnf
pysiriproxy/config/scripts/setDnsmasq.sh
pysiriproxy/connections/__init__.py
pysiriproxy/connections/connection.py
pysiriproxy/connections/iphone.py
pysiriproxy/connections/manager.py
pysiriproxy/connections/server.py
pysiriproxy/objects/__init__.py
pysiriproxy/objects/actions.py
pysiriproxy/objects/baseObject.py
pysiriproxy/objects/buttons.py
pysiriproxy/objects/commands.py
pysiriproxy/objects/dataObjects.py
pysiriproxy/objects/factory.py
pysiriproxy/objects/requests.py
pysiriproxy/objects/views.py
pysiriproxy/options/__init__.py
pysiriproxy/options/config.py
pysiriproxy/options/options.py
pysiriproxy/plugins/__init__.py
pysiriproxy/plugins/directions.py
pysiriproxy/plugins/manager.py
pysiriproxy/plugins/objectClasses.py
pysiriproxy/plugins/plugin.py
pysiriproxy/plugins/responses.py
pysiriproxy/plugins/speechRules.py
pysiriproxy/testing/__init__.py
pysiriproxy/testing/pluginTester.py
pysiriproxy/testing/testSupport.py
zopyx.pysiriproxy.egg-info/PKG-INFO
zopyx.pysiriproxy.egg-info/SOURCES.txt
zopyx.pysiriproxy.egg-info/dependency_links.txt
zopyx.pysiriproxy.egg-info/entry_points.txt
zopyx.pysiriproxy.egg-info/requires.txt
zopyx.pysiriproxy.egg-info/top_level.txt