Metadata-Version: 1.0
Name: zopyx.pysiriproxy
Version: 0.2.2
Summary: Python implementation of SiriProxy.
Home-page: https://code.google.com/p/pysiriproxy/
Author: Andreas Jung
Author-email: andreas@andreas-jung.com
License: GNU GPL v3
Platform: UNKNOWN
